MANIFEST.in
README.md
setup.py
Rdw.egg-info/PKG-INFO
Rdw.egg-info/SOURCES.txt
Rdw.egg-info/dependency_links.txt
Rdw.egg-info/not-zip-safe
Rdw.egg-info/top_level.txt
rdw/__init__.py
rdw/rdw.py
rdw/test.py