Metadata-Version: 1.1
Name: Rdw
Version: 3.0.0
Summary: (Unofficial) Python wrapper for the rdw.nl website (Netherlands Vehicle Authority) which can be used to check vehicle information.
Home-page: http://github.com/eelcohn/pypi-rdw
Author: Eelco Huininga
Author-email: eelcohn@github.com
License: MIT
Platform: UNKNOWN
Classifier: Development Status :: 4 - Beta
Classifier: Intended Audience :: Developers
Classifier: License :: OSI Approved :: MIT License
Classifier: Natural Language :: Dutch
Classifier: Programming Language :: Python :: 2 :: Only
